gpt4docstrings/__init__.py
gpt4docstrings/__main__.py
gpt4docstrings/ascii_title.py
gpt4docstrings/cli.py
gpt4docstrings/config.py
gpt4docstrings/docstring.py
gpt4docstrings/docstrings_generators/__init__.py
gpt4docstrings/docstrings_generators/base.py
gpt4docstrings/docstrings_generators/chatgpt_generator.py
gpt4docstrings/docstrings_translators/__init__.py
gpt4docstrings/docstrings_translators/base.py
gpt4docstrings/docstrings_translators/chatgpt_translator.py
gpt4docstrings/exceptions.py
gpt4docstrings/generate_docstrings.py
gpt4docstrings/prompts/__init__.py
gpt4docstrings/prompts/generation/__init__.py
gpt4docstrings/prompts/generation/chatgpt.py
gpt4docstrings/prompts/translation/__init__.py
gpt4docstrings/prompts/translation/chatgpt.py
gpt4docstrings/utils/__init__.py
gpt4docstrings/utils/decorators.py
gpt4docstrings/utils/helpers.py
gpt4docstrings/utils/parsers.py
gpt4docstrings/visit.py
gpt4docstrings-0.2.0.dist-info/LICENSE
gpt4docstrings-0.2.0.dist-info/METADATA
gpt4docstrings-0.2.0.dist-info/WHEEL
gpt4docstrings-0.2.0.dist-info/entry_points.txt
gpt4docstrings-0.2.0.dist-info/RECORD
