Metadata-Version: 2.1
Name: gpt4docstrings
Version: 0.2.0
Summary: gpt4docstrings
Home-page: https://github.com/MichaelisTrofficus/gpt4docstrings
License: MIT
Author: Miguel Otero Pedrido
Author-email: miguel.otero.pedrido.1993@gmail.com
Requires-Python: >=3.9,<4.0
Classifier: Development Status :: 3 - Alpha
Classifier: License :: OSI Approved :: MIT License
Classifier: Programming Language :: Python :: 3
Classifier: Programming Language :: Python :: 3.9
Classifier: Programming Language :: Python :: 3.10
Classifier: Programming Language :: Python :: 3.11
Requires-Dist: aiofiles (>=23.2.1,<24.0.0)
Requires-Dist: astor (>=0.8.1,<0.9.0)
Requires-Dist: asyncio (>=3.4.3,<4.0.0)
Requires-Dist: click (>=8.0.1)
Requires-Dist: colorama (>=0.4.6,<0.5.0)
Requires-Dist: docformatter (>=1.7.3,<2.0.0)
Requires-Dist: langchain (>=0.0.311,<0.0.312)
Requires-Dist: openai (>=0.27.8,<0.28.0)
Requires-Dist: pytest-mock (>=3.11.1,<4.0.0)
Requires-Dist: redbaron (>=0.9.2,<0.10.0)
Requires-Dist: reorder-python-imports (>=3.12.0,<4.0.0)
Requires-Dist: tabulate (>=0.9.0,<0.10.0)
Requires-Dist: toml (>=0.10.2,<0.11.0)
Project-URL: Changelog, https://github.com/MichaelisTrofficus/gpt4docstrings/releases
Project-URL: Documentation, https://gpt4docstrings.readthedocs.io
Project-URL: Repository, https://github.com/MichaelisTrofficus/gpt4docstrings
